{
  "run_id": "run-0013",
  "status": "ok",
  "error": "",
  "duration_ms": 92,
  "params": {
    "spike_threshold": 2.000000,
    "position_size": 2,
    "stop_loss_points": 3.000000,
    "max_hold_ticks": 50
  },
  "metrics": {
    "final_equity": 9538.800000,
    "total_pnl": -461.200000,
    "total_return": -0.046120,
    "trade_count": 48,
    "win_rate": 0.187500,
    "avg_trade_pnl": -9.608333,
    "max_drawdown": 0.055160,
    "sharpe": -0.005287,
    "fill_attempts": 859,
    "fill_rejections": 741,
    "partial_fill_count": 13,
    "requested_contracts": 1367,
    "filled_contracts": 172
  },
  "csv_stats": {
    "rows_total": 10504,
    "rows_emitted": 10504,
    "rows_skipped": 0
  }
}
